README.md
setup.cfg
setup.py
one_home_sensor/__init__.py
one_home_sensor/__main__.py
one_home_sensor/onehomesensor.py
one_home_sensor/tests.py
one_home_sensor.egg-info/PKG-INFO
one_home_sensor.egg-info/SOURCES.txt
one_home_sensor.egg-info/dependency_links.txt
one_home_sensor.egg-info/requires.txt
one_home_sensor.egg-info/top_level.txt
one_home_sensor/libs/__init__.py
one_home_sensor/libs/bme280/__init__.py