Metadata-Version: 2.1
Name: one-home-sensor
Version: 0.1.6
Summary: My home tempearture sensor for my RaspberryPi
Home-page: https://github.com/leadthesalt/one_home_sensor
Author: LeadTheSalt
Author-email: leadthesalt.soc@gmail.com
License: UNKNOWN
Platform: UNKNOWN
Classifier: Programming Language :: Python :: 3
Classifier: License :: OSI Approved :: MIT License
Classifier: Operating System :: OS Independent
Requires-Python: >=3.5
